rapt/__init__.py
rapt/rapt.py
rapt/transformers/__init__.py
rapt/transformers/base_translator.py
rapt/transformers/qtree/__init__.py
rapt/transformers/qtree/constants.py
rapt/transformers/qtree/operators.py
rapt/transformers/qtree/qtree_translator.py
rapt/transformers/sql/__init__.py
rapt/transformers/sql/sql_translator.py
rapt/treebrd/__init__.py
rapt/treebrd/attributes.py
rapt/treebrd/errors.py
rapt/treebrd/node.py
rapt/treebrd/schema.py
rapt/treebrd/treebrd.py
rapt/treebrd/utility.py
rapt/treebrd/grammars/__init__.py
rapt/treebrd/grammars/condition_grammar.py
rapt/treebrd/grammars/core_grammar.py
rapt/treebrd/grammars/extended_grammar.py
rapt/treebrd/grammars/proto_grammar.py
rapt/treebrd/grammars/syntax.py
rapt-0.0.2.dist-info/DESCRIPTION.rst
rapt-0.0.2.dist-info/METADATA
rapt-0.0.2.dist-info/metadata.json
rapt-0.0.2.dist-info/RECORD
rapt-0.0.2.dist-info/top_level.txt
rapt-0.0.2.dist-info/WHEEL
