Metadata-Version: 2.0
Name: rapt
Version: 0.0.2
Summary: Relational algebra parsing tools.
Home-page: https://github.com/pyrapt/rapt
Author: RAPT Team
Author-email: olessia.karpova@gmail.com
License: MIT
Keywords: "relational algebra" ra sql parsing pyparsing
Platform: UNKNOWN
Classifier: Development Status :: 5 - Production/Stable
Classifier: Intended Audience :: Developers
Classifier: Topic :: Education
Classifier: License :: OSI Approved :: MIT License
Classifier: Programming Language :: Python :: 3
Classifier: Programming Language :: Python :: 3.1
Classifier: Programming Language :: Python :: 3.2
Classifier: Programming Language :: Python :: 3.3
Classifier: Programming Language :: Python :: 3.4
Requires-Dist: pyparsing (>=2.0.1)
